[
    {
        "time": 1621468800000,
        "open": 2.1805,
        "close": 2.2608,
        "high": 2.2757,
        "low": 2.1077,
        "volume": 7431.4744
    },
    {
        "time": 1622073600000,
        "open": 2.176,
        "close": 2.4325,
        "high": 2.4589,
        "low": 2.106,
        "volume": 1631.9842
    },
    {
        "time": 1622678400000,
        "open": 2.4361,
        "close": 2.4436,
        "high": 2.4831,
        "low": 2.3121,
        "volume": 7861.9206
    },
    {
        "time": 1623283200000,
        "open": 2.4584,
        "close": 2.6145,
        "high": 2.6461,
        "low": 2.3512,
        "volume": 4998.1061
    },
    {
        "time": 1623888000000,
        "open": 2.5273,
        "close": 2.6497,
        "high": 2.6928,
        "low": 2.4281,
        "volume": 6749.0842
    },
    {
        "time": 1624492800000,
        "open": 2.6845,
        "close": 2.5854,
        "high": 2.6852,
        "low": 2.5466,
        "volume": 2655.0544
    },
    {
        "time": 1625097600000,
        "open": 2.542,
        "close": 3.4225,
        "high": 3.4616,
        "low": 2.4115,
        "volume": 3390.4448
    },
    {
        "time": 1625702400000,
        "open": 3.4926,
        "close": 3.3537,
        "high": 3.5317,
        "low": 3.2586,
        "volume": 8464.0597
    },
    {
        "time": 1626307200000,
        "open": 3.3505,
        "close": 3.3898,
        "high": 3.4407,
        "low": 3.1774,
        "volume": 2913.7206
    },
    {
        "time": 1626912000000,
        "open": 3.372,
        "close": 3.3902,
        "high": 3.4065,
        "low": 3.298,
        "volume": 8643.7523
    },
    {
        "time": 1627516800000,
        "open": 3.3919,
        "close": 3.4438,
        "high": 3.4544,
        "low": 3.3671,
        "volume": 9176.2213
    },
    {
        "time": 1628121600000,
        "open": 3.436,
        "close": 3.4994,
        "high": 3.5086,
        "low": 3.2829,
        "volume": 4162.2935
    },
    {
        "time": 1628726400000,
        "open": 3.4625,
        "close": 3.6161,
        "high": 3.6324,
        "low": 3.2883,
        "volume": 8739.3372
    },
    {
        "time": 1629331200000,
        "open": 3.5966,
        "close": 3.7049,
        "high": 3.7104,
        "low": 3.5427,
        "volume": 5156.2163
    },
    {
        "time": 1629936000000,
        "open": 3.7015,
        "close": 3.7664,
        "high": 3.772,
        "low": 3.5564,
        "volume": 7208.211
    }
]