[
    {
        "time": 1621468800000,
        "open": 2.1077,
        "close": 2.4605,
        "high": 2.4882,
        "low": 2.0849,
        "volume": 6907.1478
    },
    {
        "time": 1622678400000,
        "open": 2.4545,
        "close": 2.9071,
        "high": 2.9617,
        "low": 2.3685,
        "volume": 1413.8529
    },
    {
        "time": 1623283200000,
        "open": 2.9071,
        "close": 2.8096,
        "high": 2.9206,
        "low": 2.7264,
        "volume": 928.7275
    },
    {
        "time": 1623888000000,
        "open": 2.8159,
        "close": 3.19,
        "high": 3.2313,
        "low": 2.7766,
        "volume": 5739.3707
    },
    {
        "time": 1624492800000,
        "open": 3.1875,
        "close": 3.464,
        "high": 3.5218,
        "low": 3.1552,
        "volume": 904.3627
    }
]