[
    {
        "time": 1621468800000,
        "open": 2.1805,
        "close": 2.4161,
        "high": 2.4516,
        "low": 2.0924,
        "volume": 8824.265
    },
    {
        "time": 1622678400000,
        "open": 2.4108,
        "close": 2.9115,
        "high": 2.9241,
        "low": 2.3178,
        "volume": 444.4886
    },
    {
        "time": 1623283200000,
        "open": 2.8661,
        "close": 2.7435,
        "high": 2.8977,
        "low": 2.6584,
        "volume": 8849.4715
    },
    {
        "time": 1623888000000,
        "open": 2.8235,
        "close": 3.18,
        "high": 3.1996,
        "low": 2.8107,
        "volume": 1260.9139
    },
    {
        "time": 1624492800000,
        "open": 3.187,
        "close": 3.4626,
        "high": 3.5253,
        "low": 3.0814,
        "volume": 6562.0534
    }
]